simple_qsim/__init__.py
simple_qsim/gates.py
simple_qsim/vis_bloch.py
simple_qsim-0.0.3.dist-info/METADATA
simple_qsim-0.0.3.dist-info/WHEEL
simple_qsim-0.0.3.dist-info/licenses/LICENSE
simple_qsim-0.0.3.dist-info/RECORD
