Metadata-Version: 2.3
Name: simple-qsim
Version: 0.0.3
Summary: A simple Quantum Simulator
Project-URL: Homepage, https://github.com/MrPrinceRawat/Quantum-Computering-Simulator
Project-URL: Issues, https://github.com/MrPrinceRawat/Quantum-Computering-Simulator/issues
Author-email: Prince Rawat <prince@princerawat.com>
Maintainer-email: Prince Rawat <prince@princerawat.com>
License-File: LICENSE
Keywords: circuit,quantum,quantum-computing,simulator
Classifier: Development Status :: 5 - Production/Stable
Classifier: License :: OSI Approved :: GNU General Public License v3 (GPLv3)
Classifier: Operating System :: OS Independent
Classifier: Programming Language :: Python :: 3
Requires-Python: >=3.8
Requires-Dist: matplotlib
Requires-Dist: numpy
